{
  "id": "25311c2e0eb4",
  "originalPath": "/var/www/orthodox-church-mgmt/orthodoxmetrics/prod/server/scripts/README-BACKUP-SYSTEM.md",
  "relativePath": "server/scripts/README-BACKUP-SYSTEM.md",
  "name": "README-BACKUP-SYSTEM.md",
  "extension": ".md",
  "size": 9185,
  "modified": "2025-07-24T03:05:12.295Z",
  "created": "2025-07-24T03:04:54.936Z",
  "classification": {
    "type": "Documentation",
    "category": "Documentation",
    "confidence": 7
  },
  "metadata": {
    "fileStats": {
      "lines": 326,
      "characters": 9077,
      "words": 1076
    },
    "classification": {
      "type": "Documentation",
      "category": "Documentation",
      "confidence": 7
    },
    "dependencies": [],
    "security": {
      "findings": [],
      "hasSecurityIssues": false,
      "redactedContent": null
    },
    "complexity": {
      "totalLines": 326,
      "codeLines": 160,
      "commentLines": 91,
      "commentRatio": 0.36254980079681276,
      "averageLineLength": 34.569721115537845
    },
    "lastAnalyzed": "2025-07-28T07:20:00.639Z"
  },
  "contentHash": "7378a2fc6547700bd2bf935dc46810d75dbac9bef0f33e8a86104aaff7a4f31e",
  "discoveredAt": "2025-07-28T07:20:00.639Z"
}