{
  "id": "2f2240f61e19",
  "originalPath": "/var/www/orthodox-church-mgmt/orthodoxmetrics/prod/bigbook/metadata/23335e0b41ce.json",
  "relativePath": "bigbook/metadata/23335e0b41ce.json",
  "name": "23335e0b41ce.json",
  "extension": ".json",
  "size": 1279,
  "modified": "2025-07-26T04:17:11.182Z",
  "created": "2025-07-26T04:17:11.182Z",
  "classification": {
    "type": "Configuration",
    "category": "Configuration",
    "confidence": 3
  },
  "metadata": {
    "fileStats": {
      "lines": 49,
      "characters": 1279,
      "words": 93
    },
    "classification": {
      "type": "Configuration",
      "category": "Configuration",
      "confidence": 3
    },
    "dependencies": [],
    "security": {
      "findings": [],
      "hasSecurityIssues": false,
      "redactedContent": null
    },
    "complexity": {
      "totalLines": 49,
      "codeLines": 49,
      "commentLines": 0,
      "commentRatio": 0,
      "averageLineLength": 25.122448979591837
    },
    "lastAnalyzed": "2025-07-28T07:19:56.736Z"
  },
  "contentHash": "0aa0cdad893862fcd9a656ddaafa865594d6aa2851d37cfc9fa60582bfd0ecd6",
  "discoveredAt": "2025-07-28T07:19:56.736Z"
}