{
  "id": "4625d2510d8a",
  "originalPath": "/var/www/orthodox-church-mgmt/orthodoxmetrics/prod/bigbook/metadata/2c6a6d44d2ba.json",
  "relativePath": "bigbook/metadata/2c6a6d44d2ba.json",
  "name": "2c6a6d44d2ba.json",
  "extension": ".json",
  "size": 1141,
  "modified": "2025-07-26T04:17:10.946Z",
  "created": "2025-07-26T04:17:10.946Z",
  "classification": {
    "type": "Configuration",
    "category": "Configuration",
    "confidence": 3
  },
  "metadata": {
    "fileStats": {
      "lines": 43,
      "characters": 1141,
      "words": 84
    },
    "classification": {
      "type": "Configuration",
      "category": "Configuration",
      "confidence": 3
    },
    "dependencies": [],
    "security": {
      "findings": [],
      "hasSecurityIssues": false,
      "redactedContent": null
    },
    "complexity": {
      "totalLines": 43,
      "codeLines": 43,
      "commentLines": 0,
      "commentRatio": 0,
      "averageLineLength": 25.558139534883722
    },
    "lastAnalyzed": "2025-07-28T07:19:56.796Z"
  },
  "contentHash": "d7dda6d9a0ec2b4bf2bc89c8f9fe3bc65e43f6526f7ec0ffe46bfc3beb3b8fe9",
  "discoveredAt": "2025-07-28T07:19:56.796Z"
}