{
  "id": "757ce7256190",
  "originalPath": "/var/www/orthodox-church-mgmt/orthodoxmetrics/prod/server/database/fix_admin_landing_pages.sql",
  "relativePath": "server/database/fix_admin_landing_pages.sql",
  "name": "fix_admin_landing_pages.sql",
  "extension": ".sql",
  "size": 453,
  "modified": "2025-07-05T22:31:55.000Z",
  "created": "2025-07-09T00:48:35.106Z",
  "classification": {
    "type": "Database Scripts",
    "category": "Backend > Database",
    "confidence": 5
  },
  "metadata": {
    "fileStats": {
      "lines": 13,
      "characters": 453,
      "words": 57
    },
    "classification": {
      "type": "Database Scripts",
      "category": "Backend > Database",
      "confidence": 5
    },
    "dependencies": [],
    "security": {
      "findings": [],
      "hasSecurityIssues": false,
      "redactedContent": null
    },
    "complexity": {
      "totalLines": 13,
      "codeLines": 11,
      "commentLines": 0,
      "commentRatio": 0,
      "averageLineLength": 40
    },
    "lastAnalyzed": "2025-07-28T07:19:59.995Z"
  },
  "contentHash": "e9cc6403a222b4fd60ae6646e2b864f649be4bb41ae5172e2712fa45acb4aa39",
  "discoveredAt": "2025-07-28T07:19:59.995Z"
}