{
  "id": "967268ccf15a",
  "originalPath": "/var/www/orthodox-church-mgmt/orthodoxmetrics/prod/server/test-ocr-connection.js",
  "relativePath": "server/test-ocr-connection.js",
  "name": "test-ocr-connection.js",
  "extension": ".js",
  "size": 1021,
  "modified": "2025-07-19T14:03:13.010Z",
  "created": "2025-07-19T14:02:55.943Z",
  "classification": {
    "type": "Server Scripts",
    "category": "Backend > Server",
    "confidence": 3
  },
  "metadata": {
    "fileStats": {
      "lines": 38,
      "characters": 1011,
      "words": 118
    },
    "classification": {
      "type": "Server Scripts",
      "category": "Backend > Server",
      "confidence": 3
    },
    "dependencies": [],
    "security": {
      "findings": [],
      "hasSecurityIssues": false,
      "redactedContent": null
    },
    "complexity": {
      "totalLines": 38,
      "codeLines": 24,
      "commentLines": 4,
      "commentRatio": 0.14285714285714285,
      "averageLineLength": 33.535714285714285
    },
    "lastAnalyzed": "2025-07-28T07:20:01.174Z"
  },
  "contentHash": "336bf344100e7c12c3b3c8b16366a8a5d84ee91f03e2000854aadfbe74daad7f",
  "discoveredAt": "2025-07-28T07:20:01.174Z"
}