{
  "id": "a3c50a75c16f",
  "originalPath": "/var/www/orthodox-church-mgmt/orthodoxmetrics/prod/server/debug/check-port-3001.js",
  "relativePath": "server/debug/check-port-3001.js",
  "name": "check-port-3001.js",
  "extension": ".js",
  "size": 3329,
  "modified": "2025-07-22T03:58:17.742Z",
  "created": "2025-07-22T03:58:17.742Z",
  "classification": {
    "type": "Troubleshooting Utilities",
    "category": "Diagnostic Tools",
    "confidence": 3
  },
  "metadata": {
    "fileStats": {
      "lines": 79,
      "characters": 3289,
      "words": 353
    },
    "classification": {
      "type": "Troubleshooting Utilities",
      "category": "Diagnostic Tools",
      "confidence": 3
    },
    "dependencies": [
      {
        "type": "npm_package",
        "name": "child_process",
        "line": 3
      },
      {
        "type": "npm_package",
        "name": "util",
        "line": 4
      }
    ],
    "security": {
      "findings": [],
      "hasSecurityIssues": false,
      "redactedContent": null
    },
    "complexity": {
      "totalLines": 79,
      "codeLines": 64,
      "commentLines": 6,
      "commentRatio": 0.08571428571428572,
      "averageLineLength": 44.94285714285714
    },
    "lastAnalyzed": "2025-07-28T07:20:00.081Z"
  },
  "contentHash": "8f2f58bd4587ed89c7c7eb7e30fdfd3eaff6eb15deb344dda47e22d1c5595a40",
  "discoveredAt": "2025-07-28T07:20:00.081Z"
}