{
  "id": "b2a8e106bebc",
  "originalPath": "/var/www/orthodox-church-mgmt/orthodoxmetrics/prod/server/scripts/check-users-table.js",
  "relativePath": "server/scripts/check-users-table.js",
  "name": "check-users-table.js",
  "extension": ".js",
  "size": 2474,
  "modified": "2025-07-20T18:31:24.651Z",
  "created": "2025-07-20T18:30:52.806Z",
  "classification": {
    "type": "Server Scripts",
    "category": "Backend > Server",
    "confidence": 3
  },
  "metadata": {
    "fileStats": {
      "lines": 66,
      "characters": 2456,
      "words": 224
    },
    "classification": {
      "type": "Server Scripts",
      "category": "Backend > Server",
      "confidence": 3
    },
    "dependencies": [
      {
        "type": "npm_package",
        "name": "path",
        "line": 1
      }
    ],
    "security": {
      "findings": [],
      "hasSecurityIssues": false,
      "redactedContent": null
    },
    "complexity": {
      "totalLines": 66,
      "codeLines": 49,
      "commentLines": 7,
      "commentRatio": 0.125,
      "averageLineLength": 42.25
    },
    "lastAnalyzed": "2025-07-28T07:20:01.016Z"
  },
  "contentHash": "e0f26cf1062f6002586bd64e0120ec094b1d34292d3d1122e91222f28b5d2384",
  "discoveredAt": "2025-07-28T07:20:01.016Z"
}