{
  "id": "833b5f96b34f",
  "originalPath": "/var/www/orthodox-church-mgmt/orthodoxmetrics/prod/front-end/public/workspace/tsconfig.json",
  "relativePath": "front-end/public/workspace/tsconfig.json",
  "name": "tsconfig.json",
  "extension": ".json",
  "size": 508,
  "modified": "2025-07-21T03:24:48.000Z",
  "created": "2025-07-20T23:54:21.638Z",
  "classification": {
    "type": "Configuration",
    "category": "Configuration",
    "confidence": 4
  },
  "metadata": {
    "fileStats": {
      "lines": 20,
      "characters": 508,
      "words": 41
    },
    "classification": {
      "type": "Configuration",
      "category": "Configuration",
      "confidence": 4
    },
    "dependencies": [],
    "security": {
      "findings": [],
      "hasSecurityIssues": false,
      "redactedContent": null
    },
    "complexity": {
      "totalLines": 20,
      "codeLines": 20,
      "commentLines": 0,
      "commentRatio": 0,
      "averageLineLength": 24.45
    },
    "lastAnalyzed": "2025-07-28T07:19:58.640Z"
  },
  "contentHash": "444dd54545b989af7d48537e5725a0b600d0e92e3b8375c5baba476e8d613d67",
  "discoveredAt": "2025-07-28T07:19:58.640Z"
}