{
  "id": "b076c57f3a8c",
  "originalPath": "/var/www/orthodox-church-mgmt/orthodoxmetrics/prod/bigbook/metadata/36a602ca8ff1.json",
  "relativePath": "bigbook/metadata/36a602ca8ff1.json",
  "name": "36a602ca8ff1.json",
  "extension": ".json",
  "size": 1426,
  "modified": "2025-07-26T04:17:11.206Z",
  "created": "2025-07-26T04:17:11.206Z",
  "classification": {
    "type": "Configuration",
    "category": "Configuration",
    "confidence": 3
  },
  "metadata": {
    "fileStats": {
      "lines": 54,
      "characters": 1426,
      "words": 101
    },
    "classification": {
      "type": "Configuration",
      "category": "Configuration",
      "confidence": 3
    },
    "dependencies": [],
    "security": {
      "findings": [],
      "hasSecurityIssues": false,
      "redactedContent": null
    },
    "complexity": {
      "totalLines": 54,
      "codeLines": 54,
      "commentLines": 0,
      "commentRatio": 0,
      "averageLineLength": 25.425925925925927
    },
    "lastAnalyzed": "2025-07-28T07:19:56.844Z"
  },
  "contentHash": "6694753879ce0b7f2a3ec759f8c304c88ad47226e6afbdc138b9f69c821ebd06",
  "discoveredAt": "2025-07-28T07:19:56.844Z"
}