{
  "id": "b956e448e49d",
  "originalPath": "/var/www/orthodox-church-mgmt/orthodoxmetrics/prod/scripts/7-26-25/setup-omai-watchdog-system.sh",
  "relativePath": "scripts/7-26-25/setup-omai-watchdog-system.sh",
  "name": "setup-omai-watchdog-system.sh",
  "extension": ".sh",
  "size": 21824,
  "modified": "2025-07-26T06:23:19.725Z",
  "created": "2025-07-26T06:23:17.922Z",
  "classification": {
    "type": "Server Scripts",
    "category": "Backend > Server",
    "confidence": 4
  },
  "metadata": {
    "fileStats": {
      "lines": 743,
      "characters": 21232,
      "words": 2462
    },
    "classification": {
      "type": "Server Scripts",
      "category": "Backend > Server",
      "confidence": 4
    },
    "dependencies": [
      {
        "type": "npm_package",
        "name": "express",
        "line": 361
      },
      {
        "type": "npm_package",
        "name": "express-session",
        "line": 362
      },
      {
        "type": "system_command",
        "name": "npm",
        "line": 80
      }
    ],
    "security": {
      "findings": [],
      "hasSecurityIssues": false,
      "redactedContent": null
    },
    "complexity": {
      "totalLines": 743,
      "codeLines": 530,
      "commentLines": 74,
      "commentRatio": 0.12251655629139073,
      "averageLineLength": 33.913907284768214
    },
    "lastAnalyzed": "2025-07-28T07:19:59.044Z"
  },
  "contentHash": "765839c1026e5ada65fa896ba71b36b05452c46730d97e87e16153b6d8921db3",
  "discoveredAt": "2025-07-28T07:19:59.045Z"
}