{
  "id": "c572b345afec",
  "originalPath": "/var/www/orthodox-church-mgmt/orthodoxmetrics/prod/bigbook/metadata/67089e9fe0ed.json",
  "relativePath": "bigbook/metadata/67089e9fe0ed.json",
  "name": "67089e9fe0ed.json",
  "extension": ".json",
  "size": 43914,
  "modified": "2025-07-26T04:17:11.074Z",
  "created": "2025-07-26T04:17:11.074Z",
  "classification": {
    "type": "Configuration",
    "category": "Configuration",
    "confidence": 4
  },
  "metadata": {
    "fileStats": {
      "lines": 123,
      "characters": 43914,
      "words": 3757
    },
    "classification": {
      "type": "Configuration",
      "category": "Configuration",
      "confidence": 4
    },
    "dependencies": [
      {
        "type": "npm_package",
        "name": "express",
        "line": 110
      },
      {
        "type": "npm_package",
        "name": "child_process",
        "line": 110
      },
      {
        "type": "npm_package",
        "name": "fs",
        "line": 110
      },
      {
        "type": "npm_package",
        "name": "path",
        "line": 110
      },
      {
        "type": "npm_package",
        "name": "mysql2/promise",
        "line": 110
      },
      {
        "type": "npm_package",
        "name": "uuid",
        "line": 110
      }
    ],
    "security": {
      "findings": [],
      "hasSecurityIssues": false,
      "redactedContent": null
    },
    "complexity": {
      "totalLines": 123,
      "codeLines": 123,
      "commentLines": 0,
      "commentRatio": 0,
      "averageLineLength": 356.0325203252033
    },
    "lastAnalyzed": "2025-07-28T07:19:57.052Z"
  },
  "contentHash": "9efd8cfcd0a7ee9bb0d5e8ee994468279b8a4dcf51b20d5018ac7edb1e523fde",
  "discoveredAt": "2025-07-28T07:19:57.052Z"
}