{
  "id": "e461fcb58794",
  "originalPath": "/var/www/orthodox-church-mgmt/orthodoxmetrics/prod/server/database/alter-omai-memories-agents.sql",
  "relativePath": "server/database/alter-omai-memories-agents.sql",
  "name": "alter-omai-memories-agents.sql",
  "extension": ".sql",
  "size": 736,
  "modified": "2025-07-26T00:24:21.833Z",
  "created": "2025-07-26T00:24:21.022Z",
  "classification": {
    "type": "Database Scripts",
    "category": "Backend > Database",
    "confidence": 5
  },
  "metadata": {
    "fileStats": {
      "lines": 17,
      "characters": 736,
      "words": 86
    },
    "classification": {
      "type": "Database Scripts",
      "category": "Backend > Database",
      "confidence": 5
    },
    "dependencies": [],
    "security": {
      "findings": [],
      "hasSecurityIssues": false,
      "redactedContent": null
    },
    "complexity": {
      "totalLines": 17,
      "codeLines": 15,
      "commentLines": 0,
      "commentRatio": 0,
      "averageLineLength": 47.86666666666667
    },
    "lastAnalyzed": "2025-07-28T07:19:59.579Z"
  },
  "contentHash": "5cec5dbc4c9f33becf76bebb16a6d0291568395bee924bb23553077d8981bb6a",
  "discoveredAt": "2025-07-28T07:19:59.579Z"
}