{
  "timestamp": "2025-08-13T01:35:10.723Z",
  "processed": 39,
  "results": {
    "success": [
      "activity_feed",
      "admin_settings",
      "audit_logs",
      "bigbook_notes",
      "blog_categories",
      "blog_comments",
      "blog_posts",
      "calendar_settings",
      "chat_conversations",
      "chat_participants",
      "component_usage",
      "error_logs",
      "kanban_boards",
      "kanban_board_members",
      "kanban_tasks",
      "kanban_task_activity",
      "kanban_task_comments",
      "notes",
      "notifications",
      "notification_history",
      "notification_queue",
      "notification_subscriptions",
      "omai_logs",
      "omb_templates",
      "password_resets",
      "push_subscriptions",
      "questionnaire_responses",
      "refresh_tokens",
      "social_media",
      "social_reactions",
      "task_activity_log",
      "user_activity_logs",
      "user_component_summary",
      "user_notification_preferences",
      "user_profiles",
      "user_sessions",
      "user_sessions_social",
      "user_social_settings"
    ],
    "failed": [
      {
        "table": "sessions",
        "error": "Unknown column 'id' in 'sessions'"
      }
    ],
    "warnings": [
      "component_usage: Only 0/908 rows have church_id",
      "kanban_boards: Only 0/1 rows have church_id",
      "kanban_board_members: Only 0/1 rows have church_id",
      "refresh_tokens: Only 0/3 rows have church_id",
      "user_component_summary: Only 0/61 rows have church_id",
      "user_profiles: Only 0/1 rows have church_id",
      "user_social_settings: Only 0/1 rows have church_id"
    ]
  }
}